sisfft/afftc.py
sisfft/__init__.py
sisfft/utils.py
sisfft/naive.py
sisfft/timer.py
sisfft/sfft.py
sisfft/sisfft.py
sisfft-0.2.0.dist-info/METADATA
sisfft-0.2.0.dist-info/WHEEL
sisfft-0.2.0.dist-info/DESCRIPTION.rst
sisfft-0.2.0.dist-info/metadata.json
sisfft-0.2.0.dist-info/RECORD
sisfft-0.2.0.dist-info/top_level.txt
