Metadata-Version: 2.0
Name: sisfft
Version: 0.2.0
Summary: Algorithms for convolutions and p-values (tail sums) that have guaranteed relative error, even for very small values.
Home-page: https://github.com/huonw/sisfft-py
Author: Huon Wilson
Author-email: huonw@maths.usyd.edu.au
License: UNKNOWN
Download-URL: https://github.com/huonw/sisfft-py/tarball/0.2.0
Keywords: convolution,p-value,relative accuracy,log space
Platform: UNKNOWN
Classifier: License :: OSI Approved :: MIT License
Classifier: Topic :: Scientific/Engineering :: Bio-Informatics
Classifier: Topic :: Scientific/Engineering :: Mathematics
